[
    {
        "data": [
            [
                "healthy",
                "ant problems",
                "missing queen",
                "pesticide"
            ],
            [
                17.28,
                13.96,
                51.4,
                17.35
            ]
        ],
        "type": "image",
        "date": 1729477720
    },
    {
        "data": [
            [
                "healthy",
                "ant problems",
                "missing queen",
                "pesticide"
            ],
            [
                17.28,
                13.96,
                51.4,
                17.35
            ]
        ],
        "type": "image",
        "date": 1729477730
    },
    {
        "data": [
            [
                "healthy",
                "ant problems",
                "missing queen",
                "pesticide"
            ],
            [
                17.28,
                13.96,
                51.4,
                17.35
            ]
        ],
        "type": "image",
        "date": 1729477877
    },
    {
        "data": [
            [
                "healthy",
                "ant problems",
                "missing queen",
                "pesticide"
            ],
            [
                1.59,
                0.63,
                96.56,
                1.22
            ]
        ],
        "type": "image",
        "date": 1729479156
    },
    {
        "data": [
            [
                "healthy",
                "ant problems",
                "missing queen",
                "pesticide"
            ],
            [
                1.59,
                0.63,
                96.56,
                1.22
            ]
        ],
        "type": "image",
        "date": 1729479444
    },
    {
        "data": [
            [
                "healthy",
                "ant problems",
                "missing queen",
                "pesticide"
            ],
            [
                1.59,
                0.63,
                96.56,
                1.22
            ]
        ],
        "type": "image",
        "date": 1729479450
    },
    {
        "data": {},
        "type": "audio",
        "date": 1729479885
    },
    {
        "data": {},
        "type": "audio",
        "date": 1729479931
    },
    {
        "data": {},
        "type": "audio",
        "date": 1729479972
    },
    {
        "data": [
            [
                "healthy",
                "ant problems",
                "missing queen",
                "pesticide"
            ],
            [
                0.0,
                0.0,
                0.0,
                100.0
            ]
        ],
        "type": "audio",
        "date": 1729480031
    },
    {
        "data": [
            [
                "healthy",
                "ant problems",
                "missing queen",
                "pesticide"
            ],
            [
                2.21,
                0.98,
                95.18,
                1.63
            ]
        ],
        "type": "image",
        "date": 1729552216
    }
]